{
  "cate": "1",
  "date": "9æ7æ¥ 13æ22å",
  "datetime": "2018-09-07T13:22",
  "video": "",
  "duration": 0,
  "img": "html/20180907/K10011616321_1809071410_1809071426_01_02.jpg",
  "title": "人類の危機示す「環境危機時計」最も進み９時47分",
  "summary": "環境の悪化で人類がどれくらい危機的な状況になっているか、各国の政府関係者や専門家などにアンケートを行い、その結果を０時から12時までの時刻で表す「環境危機時計」が、ことしは９時47分とこれまでで最も進み、多くの人が「極めて不安」と感じていることがわかりました。",
  "more": "環境危機時計は環境の悪化で人類がどれくらい危機的な状況になっていると感じているか、毎年、東京の財団が世界各国の政府関係者や大学の専門家などにアンケートを行い、０時から12時までの時刻で回答してもらいます。<br /><br />時計が12時をさすと「環境問題で地球に人類が住めなくなる」となります。ことしは139か国、1866人から回答が得られ、平均すると時計は９時47分となりました。この時刻はアンケートを始めた1992年以降、最も進み、回答した多くの人が「極めて不安」と感じていることがわかりました。<br /><br />理由としては、およそ28％の人が地球温暖化や大雨や洪水、干ばつなどの増加といった「気候変動」を挙げました。続いて絶滅する生き物が増え「生物多様性」が失われていると答えた人が12％でした。<br /><br />また、これまで環境問題への意識が比較的低かった20代と30代の若い世代で環境悪化への危機感が高まっていることも時刻が進んだ要因の１つだということです。<br /><br />環境危機時計の取り組みを行っている旭硝子財団の清水潤一顕彰事業部長は「去年と比べて14分も進み、驚いている。時計の針が戻るよう、生活習慣や自然保護に対する意識を改めてほしい」と話していました。",
  "body": [
    {
      "title": "",
      "img": "",
      "align": "",
      "text": "",
      "textPos": ""
    }
  ],
  "relationNews": [],
  "relationLink": [],
  "word": [],
  "news_id": "k10011616321000",
  "yyyy": "2018",
  "mm": "09",
  "dd": "07",
  "url": "https://www3.nhk.or.jp/news/html/20180907/k10011616321000.html"
}