{
  "cate": "6",
  "date": "9æ24æ¥ 13æ06å",
  "datetime": "2018-09-24T13:06",
  "video": "",
  "duration": 0,
  "img": "html/20180924/K10011642101_1809241309_1809241321_01_02.jpg",
  "title": "米 過去最大の対中制裁発動 中国は同時に報復 対立激化へ",
  "summary": "アメリカのトランプ政権は、中国からの輸入品に関税を上乗せするこれまでで最大の制裁措置を日本時間の午後１時すぎに発動し、輸入品のほぼ半分が制裁の対象になりました。中国も同時に報復措置を発動し、アメリカからの輸入品の70％以上に高い関税がかけられます。",
  "more": "トランプ政権は、ワシントンで日付が24日に変わった日本時間の午後１時すぎ、中国からの2000億ドルの輸入品に10％の関税を上乗せするこれまでで最大の制裁措置を発動しました。<br /><br />対象には食料品やかばん、それに電器製品など生活に身近な製品も含まれ、これまでの措置と合わせると輸入品のほぼ半分が制裁の対象になりました。<br /><br />一方、中国もアメリカの制裁と同時にＬＮＧ＝液化天然ガスなど600億ドルの輸入品に関税をかける報復措置を発動し、アメリカからの輸入品の70％以上に関税を上乗せすることになりました。<br /><br />トランプ大統領は、「中国が報復措置をとるなら、追加で2670億ドルの制裁措置を実行する」と述べ、次は中国からのほぼすべての輸入品を制裁の対象にする構えを見せています。<br /><br />米中両国は、貿易問題を話し合うため、今月、閣僚級の協議を開くことで、一時調整に入りましたが、開催は見送りになる見通しで、両国の貿易をめぐる対立は激しくなる一方です。",
  "body": [
    {
      "title": "エスカレートする米中貿易摩擦",
      "img": "",
      "align": "",
      "text": "発端はことし３月、トランプ政権が、通商拡大法232条に基づいて鉄鋼製品に25％アルミニウムに10％の関税を上乗せして輸入を制限する措置を発動したことでした。<br /><br />これに反発した中国は、アメリカから輸入する豚肉など、128品目に高い関税をかけて対抗しました。<br /><br />トランプ政権は、それにとどまらず中国がアメリカのハイテク技術を不当に手に入れて知的財産権を侵害しているとして通商法301条に基づいて、25％の関税を上乗せする制裁措置に踏み出しました。<br /><br />ことし７月、第１弾として中国製の産業用ロボットや航空、鉄道関連の製品など818品目、340億ドル規模の輸入品に関税をかけました。対する中国はアメリカ産の大豆や牛肉、自動車など545品目に25％の関税を上乗せして報復。規模はアメリカと同じ340億ドルでした。<br /><br />第２弾は先月。アメリカは中国製のプラスチック製品や半導体、それに光ファイバーなど279品目、160億ドルの輸入品を対象にしました。中国も負けず、アメリカからの航空燃料や、ディーゼル車、医療用機器など333品目に同じ規模で報復の関税をかけて対抗しました。<br /><br />トランプ政権は、中国による報復にさらに対応をエスカレートさせ、今回第３弾の制裁として、これまでの規模を大きく上回る5745品目、2000億ドル規模の輸入品に対する関税の上乗せを発動。これまでのようなハイテク製品だけでなく、豚肉やビール、ワインなどの食品・飲料をはじめ、家具、かばん、帽子、それに掃除機や冷蔵庫といった電器製品など生活に身近な消費者向けの幅広い製品が含まれ、中国からの輸入品のほぼ半分が制裁の対象になりました。<br /><br />中国も、アメリカからのＬＮＧ＝液化天然ガスやコーヒー豆、金属加工機械、それにおもちゃなど5207品目、金額にして600億ドル規模の輸入品に関税を上乗せして対抗しました。アメリカからの輸入品の70％以上が関税上乗せの対象となりました。",
      "textPos": ""
    }
  ],
  "relationNews": [
    {
      "link": "html/20180924/k10011642021000.html",
      "title": "米中双方が関税引き上げ 対立激化へ",
      "date": "9月24日  11時16分",
      "datetime": "2018-09-24T11:16",
      "imgPath": "html/20180924/K10011642021_1809241114_1809241117_01_02.jpg",
      "iconPath": "html/20180924/K10011642021_1809241114_1809241117_02_01.jpg",
      "video": "https://www3.nhk.or.jp/news/html/20180924/movie/k10011642021_201809241208_201809241209.html",
      "duration": 68
    },
    {
      "link": "html/20180922/k10011640331000.html",
      "title": "米中 貿易問題 “閣僚級協議の開催 めど立たず”",
      "date": "9月22日  11時02分",
      "datetime": "2018-09-22T11:02",
      "imgPath": "html/20180922/K10011640331_1809221100_1809221102_01_02.jpg",
      "iconPath": "html/20180922/K10011640331_1809221100_1809221102_02_01.jpg",
      "video": "https://www3.nhk.or.jp/news/html/20180922/movie/k10011640331_201809221208_201809221209.html",
      "duration": 80
    }
  ],
  "relationLink": [
    {
      "link": "https://www3.nhk.or.jp/news/special/international-news/breakfast/",
      "title": "朝食前のあなたに…ちょっと気になる国際ニュース",
      "time": "",
      "datetime": ""
    }
  ],
  "word": [
    {
      "link": "word/0000627.html",
      "title": "米中貿易摩擦"
    },
    {
      "link": "word/0000277.html",
      "title": "トランプ大統領"
    }
  ],
  "news_id": "k10011642101000",
  "yyyy": "2018",
  "mm": "09",
  "dd": "24",
  "url": "https://www3.nhk.or.jp/news/html/20180924/k10011642101000.html"
}